heiwa4126/fizzbuzz/__init__.py
heiwa4126/fizzbuzz/cli.py
heiwa4126/fizzbuzz/fizzbuzz.py
heiwa4126/fizzbuzz/parse.py
heiwa4126.fizzbuzz-0.0.11.dist-info/LICENSE
heiwa4126.fizzbuzz-0.0.11.dist-info/METADATA
heiwa4126.fizzbuzz-0.0.11.dist-info/WHEEL
heiwa4126.fizzbuzz-0.0.11.dist-info/entry_points.txt
heiwa4126.fizzbuzz-0.0.11.dist-info/top_level.txt
heiwa4126.fizzbuzz-0.0.11.dist-info/RECORD
