Metadata-Version: 2.1
Name: heiwa4126.fizzbuzz
Version: 0.0.11
Summary: A simple fizzbuzz generator
Author: heiwa4126
Author-email: heiwa4126@gmail.com
License: MIT License
Project-URL: Repository, https://github.com/heiwa4126/pip-heiwa4126-fizzbuzz.git
Project-URL: Homepage, https://github.com/heiwa4126/pip-heiwa4126-fizzbuzz#readme
Keywords: fizzbuzz,demo
Classifier: Programming Language :: Python :: 3
Classifier: License :: OSI Approved :: MIT License
Classifier: Operating System :: OS Independent
Requires-Python: >=3.6
License-File: LICENSE
